lsdtktools/__init__.py
lsdtktools/main_window.py
lsdtopytools/LSDTribBas.py
lsdtopytools/Muddpyle.py
lsdtopytools/__init__.py
lsdtopytools/argparser_debug.py
lsdtopytools/cli.py
lsdtopytools/concavity_automator.py
lsdtopytools/fastscapelib_ultimate_binding_lsdtt.py
lsdtopytools/geoconvtools.py
lsdtopytools/lsdtopytools.py
lsdtopytools/lsdtopytools_utilities.py
lsdtopytools/numba_tools.py
lsdtopytools/quickplot.py
lsdtopytools/quickplot_ksn_knickpoints.py
lsdtopytools/quickplot_movern.py
lsdtopytools/quickplot_utilities.py
lsdtopytools/raster_loader.py
lsdtopytools/shapefile_tools.py
scripts_for_lsdtopytools/__init__.py
scripts_for_lsdtopytools/lsdtt_autoplot_tools.py
scripts_for_lsdtopytools/lsdtt_basic_operations.py
scripts_for_lsdtopytools/lsdtt_chi_ksn_knickoint_tools.py
scripts_for_lsdtopytools/lsdtt_concavity_tools.py
scripts_for_lsdtopytools/lsdtt_csv_operations.py
scripts_for_lsdtopytools/lsdtt_hypsometry.py
lsdtopytools-0.0.4.2.dist-info/AUTHORS.rst
lsdtopytools-0.0.4.2.dist-info/LICENSE
lsdtopytools-0.0.4.2.dist-info/METADATA
lsdtopytools-0.0.4.2.dist-info/WHEEL
lsdtopytools-0.0.4.2.dist-info/entry_points.txt
lsdtopytools-0.0.4.2.dist-info/top_level.txt
lsdtopytools-0.0.4.2.dist-info/RECORD
